main_common/__init__.py
main_common/apis/__init__.py
main_common/apis/test_model.py
main_common/model/__init__.py
main_common/model/load_local_model.py
main_common/model/ssd_model.py
main_common/model/saved_model/Fashion_Mnist_CNN.h5
Fashion_MNIST_CNN-0.0.4.dist-info/METADATA
Fashion_MNIST_CNN-0.0.4.dist-info/WHEEL
Fashion_MNIST_CNN-0.0.4.dist-info/top_level.txt
Fashion_MNIST_CNN-0.0.4.dist-info/RECORD
